setup.py
allejo/__init__.py
allejo/admin.py
allejo/models.py
allejo/tests.py
allejo/views.py
allejo/migrations/0001_initial.py
allejo/migrations/__init__.py
allejo/south_migrations/0001_initial.py
allejo/south_migrations/__init__.py
django_allejo.egg-info/PKG-INFO
django_allejo.egg-info/SOURCES.txt
django_allejo.egg-info/dependency_links.txt
django_allejo.egg-info/top_level.txt