Metadata-Version: 1.1
Name: django-allejo
Version: 0.1.0
Summary: Management and creation for custom tournaments and rankings for many sports.
Home-page: http://github.com/lerrua/django-allejo
Author: Igor P. Leroy
Author-email: ip.leroy@gmail.com
License: BSD
Keywords: standings,soccer,football,ranking
Platform: UNKNOWN
Classifier: Development Status :: 4 - Beta
Classifier: Intended Audience :: Developers
Classifier: License :: OSI Approved :: Apache Software License
Classifier: Programming Language :: Python
Classifier: Operating System :: OS Independent
Classifier: Topic :: Software Development :: Libraries
Classifier: Topic :: Utilities
Classifier: Environment :: Web Environment
Classifier: Framework :: Django
